pypiLibrary/__init__.py
pypilibrary-0.1.dist-info/LICENCE.txt
pypilibrary-0.1.dist-info/METADATA
pypilibrary-0.1.dist-info/WHEEL
pypilibrary-0.1.dist-info/top_level.txt
pypilibrary-0.1.dist-info/RECORD
