Metadata-Version: 2.2
Name: pypiLibrary
Version: 0.1
Summary: This is a very basic calculator
Author: Shreya
Author-email: shreyaneelam242@gmail.com
Classifier: Programming Language :: Python :: 3
Classifier: License :: OSI Approved :: MIT License
Classifier: Operating System :: OS Independent
License-File: LICENCE.txt
Dynamic: author
Dynamic: author-email
Dynamic: classifier
Dynamic: summary
